snaps/__init__.py
snaps/custom_image_test_runner.py
snaps/file_utils.py
snaps/playbook_runner.py
snaps/test_runner.py
snaps/test_suite_builder.py
snaps/domain/__init__.py
snaps/domain/flavor.py
snaps/domain/image.py
snaps/domain/keypair.py
snaps/domain/network.py
snaps/domain/project.py
snaps/domain/role.py
snaps/domain/stack.py
snaps/domain/user.py
snaps/domain/vm_inst.py
snaps/domain/test/__init__.py
snaps/domain/test/flavor_tests.py
snaps/domain/test/image_tests.py
snaps/domain/test/keypair_tests.py
snaps/domain/test/network_tests.py
snaps/domain/test/project_tests.py
snaps/domain/test/role_tests.py
snaps/domain/test/stack_tests.py
snaps/domain/test/user_tests.py
snaps/domain/test/vm_inst_tests.py
snaps/openstack/__init__.py
snaps/openstack/create_flavor.py
snaps/openstack/create_image.py
snaps/openstack/create_instance.py
snaps/openstack/create_keypairs.py
snaps/openstack/create_network.py
snaps/openstack/create_project.py
snaps/openstack/create_router.py
snaps/openstack/create_security_group.py
snaps/openstack/create_stack.py
snaps/openstack/create_user.py
snaps/openstack/os_credentials.py
snaps/openstack/tests/__init__.py
snaps/openstack/tests/create_flavor_tests.py
snaps/openstack/tests/create_image_tests.py
snaps/openstack/tests/create_instance_tests.py
snaps/openstack/tests/create_keypairs_tests.py
snaps/openstack/tests/create_network_tests.py
snaps/openstack/tests/create_project_tests.py
snaps/openstack/tests/create_router_tests.py
snaps/openstack/tests/create_security_group_tests.py
snaps/openstack/tests/create_stack_tests.py
snaps/openstack/tests/create_user_tests.py
snaps/openstack/tests/openstack_tests.py
snaps/openstack/tests/os_source_file_test.py
snaps/openstack/tests/validation_utils.py
snaps/openstack/tests/conf/__init__.py
snaps/openstack/tests/conf/os_credentials_tests.py
snaps/openstack/tests/conf/os_env.yaml.template
snaps/openstack/tests/conf/overcloudrc_test
snaps-5.0.0.dist-info/DESCRIPTION.rst
snaps-5.0.0.dist-info/METADATA
snaps-5.0.0.dist-info/RECORD
snaps-5.0.0.dist-info/WHEEL
snaps-5.0.0.dist-info/metadata.json
snaps-5.0.0.dist-info/pbr.json
snaps-5.0.0.dist-info/top_level.txt
