Metadata-Version: 2.0
Name: snaps
Version: 5.0.0
Summary: UNKNOWN
Home-page: https://gerrit.opnfv.org/gerrit/gitweb?p=snaps.git;a=summary
Author: Steve Pisarski
Author-email: s.pisarski@cablelabs.com
License: UNKNOWN
Platform: UNKNOWN
Requires-Dist: ansible (>=2.1.0)
Requires-Dist: cryptography (>=1.0,!=1.3.0)
Requires-Dist: python-glanceclient (>=2.5.0)
Requires-Dist: python-heatclient (>=1.6.1)
Requires-Dist: python-keystoneclient (>=3.8.0)
Requires-Dist: python-neutronclient (>=5.1.0)
Requires-Dist: python-novaclient (!=7.0.0,>=6.0.0)
Requires-Dist: scp
Requires-Dist: wrapt (>=1.7.0)
